src/seg_decoder.v
module seg_decoder(input wire [3:0] bcd, output reg [7:0] seg_data);
    always @* begin
        case (bcd)
            0:seg_data=8'hfc; 1:seg_data=8'h60; 2:seg_data=8'hda; 3:seg_data=8'hf2;
            4:seg_data=8'h66; 5:seg_data=8'hb6; 6:seg_data=8'hbe; 7:seg_data=8'he0;
            8:seg_data=8'hfe; 9:seg_data=8'hf6; 10:seg_data=8'hee; 11:seg_data=8'h3e;
            12:seg_data=8'h9c; 13:seg_data=8'h7a; 14:seg_data=8'h9e; 15:seg_data=8'h8e;
            default: seg_data=8'h00;
        endcase
    end
endmodule

sim/tb_seg_decoder.sv
`timescale 1ns/1ps
module tb_seg_decoder;
    reg [3:0] bcd;
    wire [7:0] seg_data;
    reg [7:0] digits[0:15];
    seg_decoder dut(bcd,seg_data);
    integer n,checked=0;
    reg [7:0] expected;

    initial begin
        $dumpfile("wave.vcd");
        $dumpvars(0,tb_seg_decoder);

        digits[0]=8'hfc; digits[1]=8'h60; digits[2]=8'hda; digits[3]=8'hf2;
        digits[4]=8'h66; digits[5]=8'hb6; digits[6]=8'hbe; digits[7]=8'he0;
        digits[8]=8'hfe; digits[9]=8'hf6; digits[10]=8'hee; digits[11]=8'h3e;
        digits[12]=8'h9c; digits[13]=8'h7a; digits[14]=8'h9e; digits[15]=8'h8e;

        for(n=0;n<16;n=n+1) begin
            bcd=n;
            expected=digits[n];
            #10;
            if (seg_data !== expected)
                $fatal(1,"FAIL seg_decoder vector=%0d expected=%h actual=%h",n,expected,seg_data);
            checked=checked+1;
        end
        if(checked!=16) $fatal(1,"Incomplete test");
        $display("LAB1_PASS seg_decoder cases=%0d",checked);
        $finish;
    end

    initial begin #100000; $fatal(1,"Watchdog"); end
endmodule

evidence/wave.vcd
$date
	Mon Sep 14 03:50:51 2026
$end
$version
	Icarus Verilog
$end
$timescale
	1ps
$end
$scope module tb_seg_decoder $end
$var wire 8 ! seg_data [7:0] $end
$var reg 4 " bcd [3:0] $end
$var reg 8 # expected [7:0] $end
$var integer 32 $ checked [31:0] $end
$var integer 32 % n [31:0] $end
$scope module dut $end
$var wire 4 & bcd [3:0] $end
$var reg 8 ' seg_data [7:0] $end
$upscope $end
$upscope $end
$enddefinitions $end
$comment Show the parameter values. $end
$dumpall
$end
#0
$dumpvars
b11111100 '
b0 &
b0 %
b0 $
b11111100 #
b0 "
b11111100 !
$end
#10000
b1100000 !
b1100000 '
b1100000 #
b1 "
b1 &
b1 %
b1 $
#20000
b11011010 !
b11011010 '
b11011010 #
b10 "
b10 &
b10 %
b10 $
#30000
b11110010 !
b11110010 '
b11110010 #
b11 "
b11 &
b11 %
b11 $
#40000
b1100110 !
b1100110 '
b1100110 #
b100 "
b100 &
b100 %
b100 $
#50000
b10110110 !
b10110110 '
b10110110 #
b101 "
b101 &
b101 %
b101 $
#60000
b10111110 !
b10111110 '
b10111110 #
b110 "
b110 &
b110 %
b110 $
#70000
b11100000 !
b11100000 '
b11100000 #
b111 "
b111 &
b111 %
b111 $
#80000
b11111110 !
b11111110 '
b11111110 #
b1000 "
b1000 &
b1000 %
b1000 $
#90000
b11110110 !
b11110110 '
b11110110 #
b1001 "
b1001 &
b1001 %
b1001 $
#100000
b11101110 !
b11101110 '
b11101110 #
b1010 "
b1010 &
b1010 %
b1010 $
#110000
b111110 !
b111110 '
b111110 #
b1011 "
b1011 &
b1011 %
b1011 $
#120000
b10011100 !
b10011100 '
b10011100 #
b1100 "
b1100 &
b1100 %
b1100 $
#130000
b1111010 !
b1111010 '
b1111010 #
b1101 "
b1101 &
b1101 %
b1101 $
#140000
b10011110 !
b10011110 '
b10011110 #
b1110 "
b1110 &
b1110 %
b1110 $
#150000
b10001110 !
b10001110 '
b10001110 #
b1111 "
b1111 &
b1111 %
b1111 $
#160000
b10000 %
b10000 $
